scons_tool_util-0.2.0-py3.8-nspkg.pth
sconstool/util/__init__.py
sconstool/util/about.py
sconstool/util/emitter_.py
sconstool/util/finder_.py
sconstool/util/imports_.py
sconstool/util/misc_.py
sconstool/util/replacements_.py
sconstool/util/selector_.py
scons_tool_util-0.2.0.dist-info/METADATA
scons_tool_util-0.2.0.dist-info/WHEEL
scons_tool_util-0.2.0.dist-info/namespace_packages.txt
scons_tool_util-0.2.0.dist-info/top_level.txt
scons_tool_util-0.2.0.dist-info/RECORD
