Metadata-Version: 2.1
Name: scons-tool-util
Version: 0.2.0
Summary: A library of utility functions and objects for scons-tool-* packages
Home-page: https://github.com/ptomulik/scons-tool-util
Author: Paweł Tomulik
Author-email: ptomulik@meil.pw.edu.pl
License: UNKNOWN
Platform: UNKNOWN
